build/lib/build/lib/build/lib/build/lib/build/lib/ghapi/__init__.py
build/lib/build/lib/build/lib/build/lib/build/lib/ghapi/connection.py
build/lib/build/lib/build/lib/build/lib/build/lib/ghapi/exceptions.py
build/lib/build/lib/build/lib/build/lib/build/lib/ghapi/pulls.py
build/lib/build/lib/build/lib/build/lib/build/lib/ghapi/repos.py
build/lib/build/lib/build/lib/build/lib/build/lib/ghapi/reviews.py
build/lib/build/lib/build/lib/build/lib/build/lib/ghapi/search.py
build/lib/build/lib/build/lib/build/lib/build/lib/ghapi/users.py
build/lib/build/lib/build/lib/build/lib/build/lib/ghapi/utils.py
build/lib/build/lib/build/lib/build/lib/build/lib/ghapi/version.py
build/lib/build/lib/build/lib/build/lib/ghapi/__init__.py
build/lib/build/lib/build/lib/build/lib/ghapi/connection.py
build/lib/build/lib/build/lib/build/lib/ghapi/exceptions.py
build/lib/build/lib/build/lib/build/lib/ghapi/pulls.py
build/lib/build/lib/build/lib/build/lib/ghapi/repos.py
build/lib/build/lib/build/lib/build/lib/ghapi/reviews.py
build/lib/build/lib/build/lib/build/lib/ghapi/search.py
build/lib/build/lib/build/lib/build/lib/ghapi/users.py
build/lib/build/lib/build/lib/build/lib/ghapi/utils.py
build/lib/build/lib/build/lib/build/lib/ghapi/version.py
build/lib/build/lib/build/lib/ghapi/__init__.py
build/lib/build/lib/build/lib/ghapi/connection.py
build/lib/build/lib/build/lib/ghapi/exceptions.py
build/lib/build/lib/build/lib/ghapi/pulls.py
build/lib/build/lib/build/lib/ghapi/repos.py
build/lib/build/lib/build/lib/ghapi/reviews.py
build/lib/build/lib/build/lib/ghapi/search.py
build/lib/build/lib/build/lib/ghapi/users.py
build/lib/build/lib/build/lib/ghapi/utils.py
build/lib/build/lib/build/lib/ghapi/version.py
build/lib/build/lib/ghapi/__init__.py
build/lib/build/lib/ghapi/connection.py
build/lib/build/lib/ghapi/exceptions.py
build/lib/build/lib/ghapi/pulls.py
build/lib/build/lib/ghapi/repos.py
build/lib/build/lib/ghapi/reviews.py
build/lib/build/lib/ghapi/search.py
build/lib/build/lib/ghapi/users.py
ghapi_client-0.3.1.dist-info/LICENSE
ghapi_client-0.3.1.dist-info/METADATA
ghapi_client-0.3.1.dist-info/WHEEL
ghapi_client-0.3.1.dist-info/top_level.txt
ghapi_client-0.3.1.dist-info/zip-safe
ghapi_client-0.3.1.dist-info/RECORD
