Metadata-Version: 2.1
Name: ghapi-client
Version: 0.3.1
Summary: Python client for the GitHub API
Author-email: François-Guillaume Fernandez <fg-feedback@protonmail.com>
License: Apache License
Project-URL: documentation, https://frgfm.github.io/ghapi
Project-URL: repository, https://github.com/frgfm/ghapi
Project-URL: tracker, https://github.com/frgfm/ghapi/issues
Keywords: python
Classifier: Development Status :: 4 - Beta
Classifier: Intended Audience :: Developers
Classifier: License :: OSI Approved :: Apache Software License
Classifier: Natural Language :: English
Classifier: Operating System :: OS Independent
Classifier: Programming Language :: Python :: 3
Classifier: Programming Language :: Python :: 3.6
Classifier: Programming Language :: Python :: 3.7
Classifier: Programming Language :: Python :: 3.8
Classifier: Programming Language :: Python :: 3.9
Classifier: Topic :: Software Development
Classifier: Topic :: Software Development :: Libraries
Classifier: Topic :: Software Development :: Libraries :: Python Modules
Requires-Python: <4,>=3.6
License-File: LICENSE
Requires-Dist: requests (<3.0.0,>=2.24.0)
Provides-Extra: dev
Requires-Dist: pytest (>=7.2.0) ; extra == 'dev'
Requires-Dist: coverage[toml] (>=4.5.4) ; extra == 'dev'
Requires-Dist: flake8 (>=3.9.0) ; extra == 'dev'
Requires-Dist: isort (>=5.7.0) ; extra == 'dev'
Requires-Dist: mypy (>=0.812) ; extra == 'dev'
Requires-Dist: pydocstyle[toml] (>=6.0.0) ; extra == 'dev'
Requires-Dist: black (<23.0,>=22.1) ; extra == 'dev'
Requires-Dist: autoflake (<2.0.0,>=1.5.0) ; extra == 'dev'
Requires-Dist: bandit[toml] (<1.8.0,>=1.7.0) ; extra == 'dev'
Requires-Dist: pre-commit (<3.0.0,>=2.17.0) ; extra == 'dev'
Requires-Dist: sphinx (<=3.4.3) ; extra == 'dev'
Requires-Dist: sphinx-rtd-theme (==0.4.3) ; extra == 'dev'
Requires-Dist: sphinxemoji (>=0.1.8) ; extra == 'dev'
Requires-Dist: sphinx-copybutton (>=0.3.1) ; extra == 'dev'
Requires-Dist: docutils (<0.18) ; extra == 'dev'
Requires-Dist: recommonmark (>=0.7.1) ; extra == 'dev'
Requires-Dist: sphinx-markdown-tables (>=0.0.15) ; extra == 'dev'
Requires-Dist: Jinja2 (<3.1) ; extra == 'dev'
Provides-Extra: docs
Requires-Dist: sphinx (!=3.5.0,>=3.0.0) ; extra == 'docs'
Requires-Dist: sphinxemoji (>=0.1.8) ; extra == 'docs'
Requires-Dist: sphinx-copybutton (>=0.3.1) ; extra == 'docs'
Requires-Dist: docutils (<0.18) ; extra == 'docs'
Requires-Dist: recommonmark (>=0.7.1) ; extra == 'docs'
Requires-Dist: sphinx-markdown-tables (>=0.0.15) ; extra == 'docs'
Requires-Dist: Jinja2 (<3.1) ; extra == 'docs'
Requires-Dist: furo (>=2022.3.4) ; extra == 'docs'
Provides-Extra: quality
Requires-Dist: flake8 (>=3.9.0) ; extra == 'quality'
Requires-Dist: isort (>=5.7.0) ; extra == 'quality'
Requires-Dist: mypy (>=0.812) ; extra == 'quality'
Requires-Dist: pydocstyle[toml] (>=6.0.0) ; extra == 'quality'
Requires-Dist: black (<23.0,>=22.1) ; extra == 'quality'
Requires-Dist: autoflake (<2.0.0,>=1.5.0) ; extra == 'quality'
Requires-Dist: bandit[toml] (<1.8.0,>=1.7.0) ; extra == 'quality'
Requires-Dist: pre-commit (<3.0.0,>=2.17.0) ; extra == 'quality'
Provides-Extra: test
Requires-Dist: pytest (>=7.2.0) ; extra == 'test'
Requires-Dist: coverage[toml] (>=4.5.4) ; extra == 'test'
